{"type":"FeatureCollection","features":[{"type":"Feature","properties":{"marker-color":"#7e7e7e","marker-size":"medium","marker-symbol":"","name":"4th Avenue Des Plaines Illinois"},"geometry":{"type":"Point","coordinates":[-87.90410041809082,42.04296660526501]}},{"type":"Feature","properties":{},"geometry":{"type":"Point","coordinates":[-87.89991617202759,42.043094088227846]}},{"type":"Feature","properties":{},"geometry":{"type":"Point","coordinates":[-87.89598941802979,42.04325344157169]}},{"type":"Feature","properties":{},"geometry":{"type":"Point","coordinates":[-87.89564609527588,42.0432853121925]}},{"type":"Feature","properties":{},"geometry":{"type":"Point","coordinates":[-87.89523839950562,42.04223357326489]}},{"type":"Feature","properties":{},"geometry":{"type":"Point","coordinates":[-87.89463758468627,42.04205828175104]}},{"type":"Feature","properties":{},"geometry":{"type":"Point","coordinates":[-87.89356470108032,42.04169176156853]}},{"type":"Feature","properties":{},"geometry":{"type":"Point","coordinates":[-87.8931999206543,42.04124556023185]}},{"type":"Feature","properties":{},"geometry":{"type":"Point","coordinates":[-87.89270639419556,42.04142085398778]}},{"type":"Feature","properties":{},"geometry":{"type":"Point","coordinates":[-87.8921914100647,42.041452725527826]}},{"type":"Feature","properties":{},"geometry":{"type":"Point","coordinates":[-87.88899421691895,42.04013004318179]}},{"type":"Feature","properties":{},"geometry":{"type":"Point","coordinates":[-87.88803935050964,42.04111807356015]}},{"type":"Feature","properties":{},"geometry":{"type":"Point","coordinates":[-87.88774967193604,42.04109416978071]}},{"type":"Feature","properties":{"marker-color":"#7e7e7e","marker-size":"medium","marker-symbol":"","name":"1501 Ellinwood Street"},"geometry":{"type":"Point","coordinates":[-87.88694500923157,42.04079935576182]}}]}